{
  "project_info": {
    "project_number": "707448923009",
    "project_id": "farmerfact-67bca",
    "storage_bucket": "farmerfact-67bca.appspot.com"
  },
  "client": [
    {
      "client_info": {
        "mobilesdk_app_id": "1:707448923009:android:304e37b4f242723aef7e80",
        "android_client_info": {
          "package_name": "com.latrosoft.farmerfact"
        }
      },
      "oauth_client": [
        {
          "client_id": "707448923009-a8red5dc7rmru6dkm2f2l3l4lv0pu01s.apps.googleusercontent.com",
          "client_type": 3
        }
      ],
      "api_key": [
        {
          "current_key": "AIzaSyBgpZzsXKS2iAVVXa8auakWIaU-43RqmXQ"
        }
      ],
      "services": {
        "appinvite_service": {
          "other_platform_oauth_client": [
            {
              "client_id": "707448923009-a8red5dc7rmru6dkm2f2l3l4lv0pu01s.apps.googleusercontent.com",
              "client_type": 3
            }
          ]
        }
      }
    }
  ],
  "configuration_version": "1"
}